{
  "kind": "collectionType",
  "collectionName": "assets",
  "info": {
    "singularName": "asset",
    "pluralName": "assets",
    "displayName": "Asset",
    "description": ""
  },
  "options": {
    "draftAndPublish": true
  },
  "pluginOptions": {
    "i18n": {
      "localized": true
    }
  },
  "attributes": {
    "Name": {
      "pluginOptions": {
        "i18n": {
          "localized": true
        },
        "translate": {
          "translate": "translate"
        }
      },
      "type": "string"
    },
    "userGroup": {
      "type": "relation",
      "relation": "manyToOne",
      "target": "plugin::multi-tenant.user-group",
      "pluginOptions": {
        "translate": {
          "translate": "translate"
        }
      },
      "inversedBy": "assets"
    }
  }
}
